moutils/__init__.py
moutils/oauth.py
moutils/static/cookies.js
moutils/static/copy.js
moutils/static/device_flow.css
moutils/static/device_flow.js
moutils/static/hash.js
moutils/static/path.js
moutils/static/pkce_flow.css
moutils/static/pkce_flow.js
moutils/static/query.js
moutils/static/shell.js
moutils/static/slot.js
moutils/static/storage.js
moutils/static/urlinfo.js
moutils-0.3.12.dist-info/METADATA
moutils-0.3.12.dist-info/WHEEL
moutils-0.3.12.dist-info/licenses/LICENSE
moutils-0.3.12.dist-info/RECORD
