Metadata-Version: 2.4
Name: moutils
Version: 0.3.12
License-File: LICENSE
Requires-Dist: anywidget
Requires-Dist: marimo>=0.11.0
Requires-Dist: requests>=2.30.0
Provides-Extra: dev
Requires-Dist: marimo; extra == 'dev'
